{
  "animateLoading": true,
  "bottomRow": 31,
  "capSide": 0,
  "capType": "nc",
  "displayName": "Divider",
  "dividerColor": "#858282",
  "dynamicBindingPathList": [],
  "hideCard": false,
  "iconSVG": "https://appcdn.appsmith.com/static/media/icon.3b7d47d7bd70da418a827287042cbb7f.svg",
  "isDeprecated": false,
  "isLoading": false,
  "isVisible": true,
  "key": "5434wpyrq2",
  "leftColumn": 0,
  "minWidth": 450,
  "mobileBottomRow": 33,
  "mobileLeftColumn": 0,
  "mobileRightColumn": 11,
  "mobileTopRow": 29,
  "orientation": "horizontal",
  "originalBottomRow": 31,
  "originalTopRow": 27,
  "parentColumnSpace": 19.296875,
  "parentId": "0",
  "parentRowSpace": 10,
  "renderMode": "CANVAS",
  "responsiveBehavior": "fill",
  "rightColumn": 64,
  "searchTags": [
    "line"
  ],
  "strokeStyle": "solid",
  "tags": [
    "Layout"
  ],
  "thickness": 2,
  "topRow": 27,
  "type": "DIVIDER_WIDGET",
  "version": 1,
  "widgetId": "k4ocw2tizw",
  "widgetName": "Divider1"
}